pvxarray/__init__.py
pvxarray/_version.py
pvxarray/accessor.py
pvxarray/errors.py
pvxarray/io.py
pvxarray/points.py
pvxarray/rectilinear.py
pvxarray/report.py
pvxarray/structured.py
pvxarray/vtk_source.py
pvxarray/widgets.py
pyvista_xarray-0.1.7.dist-info/LICENSE
pyvista_xarray-0.1.7.dist-info/METADATA
pyvista_xarray-0.1.7.dist-info/NOTICE
pyvista_xarray-0.1.7.dist-info/WHEEL
pyvista_xarray-0.1.7.dist-info/entry_points.txt
pyvista_xarray-0.1.7.dist-info/top_level.txt
pyvista_xarray-0.1.7.dist-info/RECORD
