Metadata-Version: 2.1
Name: pyvista-xarray
Version: 0.1.7
Summary: xarray DataArray accessors for PyVista
Home-page: https://github.com/pyvista/pyvista-xarray
Author: Kitware, Inc.
Author-email: kitware@kitware.com
License: UNKNOWN
Platform: UNKNOWN
Classifier: Development Status :: 3 - Alpha
Classifier: License :: OSI Approved :: Apache Software License
Classifier: Operating System :: OS Independent
Classifier: Programming Language :: Python :: 3
Classifier: Programming Language :: Python :: 3.9
Classifier: Programming Language :: Python :: 3.10
Classifier: Programming Language :: Python :: 3.11
Classifier: Programming Language :: Python
Requires-Python: >=3.9
License-File: LICENSE
License-File: NOTICE
